tidycsv/__init__.py
tidycsv/core/__init__.py
tidycsv/core/parsing.py
tidycsv/interface.py
tidycsv/utils/__init__.py
tidycsv/utils/customobjs.py
tidycsv-0.1.2.dist-info/LICENSE
tidycsv-0.1.2.dist-info/WHEEL
tidycsv-0.1.2.dist-info/METADATA
tidycsv-0.1.2.dist-info/RECORD
