Metadata-Version: 2.1
Name: tidycsv
Version: 0.1.2
Summary: A minimalistic solution to messy CSV files.
Home-page: https://github.com/gmagannaDevelop/tidyCSV.py
License: MIT
Author: Gustavo Magaña López
Author-email: gmaganna.biomed@gmail.com
Requires-Python: >=3.8,<4.0
Classifier: License :: OSI Approved :: MIT License
Classifier: Programming Language :: Python :: 3
Classifier: Programming Language :: Python :: 3.8
Classifier: Programming Language :: Python :: 3.9
Project-URL: Repository, https://github.com/gmagannaDevelop/tidyCSV.py
